psgresizer/LICENSE.txt
psgresizer/README.md
psgresizer/__init__.py
psgresizer/__main__.py
psgresizer/psgresizer.ico
psgresizer/psgresizer.py
psgresizer/screenshot.jpg
psgresizer-5.0.0.dist-info/LICENSE.txt
psgresizer-5.0.0.dist-info/METADATA
psgresizer-5.0.0.dist-info/WHEEL
psgresizer-5.0.0.dist-info/entry_points.txt
psgresizer-5.0.0.dist-info/top_level.txt
psgresizer-5.0.0.dist-info/RECORD
