Metadata-Version: 2.1
Name: psgresizer
Version: 5.0.0
Summary: PySimpleGUI  application / utility to resize your images and encode them to Bas64 format.
Home-page: https://github.com/PySimpleGUI/psgresizer
Author: PySimpleSoft Inc.
License: Free To Use But Restricted
Keywords: GUI UI PySimpleGUI tkinter psgresizer base64 resize pil pillow
Classifier: Development Status :: 5 - Production/Stable
Classifier: Intended Audience :: Developers
Classifier: License :: Free To Use But Restricted
Classifier: Operating System :: OS Independent
Classifier: Framework :: PySimpleGUI
Classifier: Framework :: PySimpleGUI :: 5
Classifier: Programming Language :: Python :: 3
Classifier: Programming Language :: Python :: 3.6
Classifier: Programming Language :: Python :: 3.7
Classifier: Programming Language :: Python :: 3.8
Classifier: Programming Language :: Python :: 3.9
Classifier: Programming Language :: Python :: 3.10
Classifier: Programming Language :: Python :: 3.11
Classifier: Programming Language :: Python :: 3.12
Classifier: Programming Language :: Python :: 3.13
Classifier: Topic :: Multimedia :: Graphics
Classifier: Topic :: Software Development :: User Interfaces
Requires-Python: >=3.6
License-File: LICENSE.txt
Requires-Dist: PySimpleGUI >=5
Requires-Dist: Pillow
